odoo10_addon_purchase_variant_configurator-10.0.2.2.0-py2.7-nspkg.pth
odoo/addons/purchase_variant_configurator/README.rst
odoo/addons/purchase_variant_configurator/__init__.py
odoo/addons/purchase_variant_configurator/__manifest__.py
odoo/addons/purchase_variant_configurator/hooks.py
odoo/addons/purchase_variant_configurator/i18n/es.po
odoo/addons/purchase_variant_configurator/i18n/fr.po
odoo/addons/purchase_variant_configurator/i18n/hr.po
odoo/addons/purchase_variant_configurator/i18n/it.po
odoo/addons/purchase_variant_configurator/i18n/pt_BR.po
odoo/addons/purchase_variant_configurator/i18n/purchase_variant_configurator.pot
odoo/addons/purchase_variant_configurator/i18n/ro.po
odoo/addons/purchase_variant_configurator/i18n/sl.po
odoo/addons/purchase_variant_configurator/migrations/8.0.2.0.0/pre-migration.py
odoo/addons/purchase_variant_configurator/models/__init__.py
odoo/addons/purchase_variant_configurator/models/purchase_order_line.py
odoo/addons/purchase_variant_configurator/tests/__init__.py
odoo/addons/purchase_variant_configurator/tests/test_purchase_order.py
odoo/addons/purchase_variant_configurator/views/inherited_purchase_order_views.xml
odoo10_addon_purchase_variant_configurator-10.0.2.2.0.dist-info/METADATA
odoo10_addon_purchase_variant_configurator-10.0.2.2.0.dist-info/RECORD
odoo10_addon_purchase_variant_configurator-10.0.2.2.0.dist-info/WHEEL
odoo10_addon_purchase_variant_configurator-10.0.2.2.0.dist-info/namespace_packages.txt
odoo10_addon_purchase_variant_configurator-10.0.2.2.0.dist-info/top_level.txt
