Metadata-Version: 2.1
Name: odoo10-addon-purchase-variant-configurator
Version: 10.0.2.2.0
Summary: Product variants in purchase management
Home-page: http://www.odoomrp.com
Author: AvanzOSC, Tecnativa, ACSONE SA/NV,Odoo Community Association (OCA)
Author-email: support@odoo-community.org
License: AGPL-3
Platform: UNKNOWN
Classifier: Programming Language :: Python
Classifier: Framework :: Odoo
Classifier: License :: OSI Approved :: GNU Affero General Public License v3
Requires-Python: ~=2.7
Requires-Dist: odoo10-addon-product-variant-configurator
Requires-Dist: odoo (<10.1dev,>=10.0)
